{"index": "3.4.10", "image": "resized_images/Tale of Yayati.png", "text": " Nahush had six sons- Yati, Yayati, Sanyati, Aayati, Viyati and Kriti.\n Yayati had two wives, Devyani, the daughter of Shukracharya and Sharmishtha, the daughter of Vrishparva.\n Devyani gave birth to Yadu and Turvasu whereas Sharmishtha gave birth to Druhayu, Anu and Puru.\n Because of a curse of Shukracharya old age had descended on Yayati prematurely.\n Yayati then requested his eldest son Yadu to exchange his youth with his old age but Yadu refused.\n Then Yayati requested each of his sons one by one but all of them refused plainly for the fear of getting old prematurely.\n At last Yayati\u2019s youngest son Puru gladly accepted his request and gave him his youth.\n Regaining the youth, Yayati once again indulged in carnal pleasures with both his queens.\n But everyday his desire for pleasures increased like a fire flared up by ghee.\n After one thousand years Yayati realised his mistake and decided to expiate for his sin.\n Thus, Yayati returned Puru his youth and acquired his old age once again.\n Then crowning Puru as the king, he took an exile to the forest. ", "next": "3.4.11", "prev": "3.4.9", "title": "Tale of Yayati"}