{"index": "5.6.3", "image": "resized_images/Methods of Shiva Worship.png", "text": " A Sanyasi should paste the ground with cow dung and construct a quadrangular 'Mandap'. He should then keep a broad leaf of Palm tree at its centre. He should then fence the area with coloured threads from all the four directions. After that he should draw a eight petalled flower in the centre of the Mandap, upon which he should draw a Shiva Yantra. At last he can commence his worship of the Sun god. ", "next": "5.6.4", "prev": "5.6.2", "title": "Methods of Shiva Worship"}